wrap_docstrings/__init__.py
wrap_docstrings-0.1.0a3.dist-info/WHEEL
wrap_docstrings-0.1.0a3.dist-info/entry_points.txt
wrap_docstrings-0.1.0a3.dist-info/METADATA
wrap_docstrings-0.1.0a3.dist-info/RECORD
