Metadata-Version: 2.3
Name: wrap-docstrings
Version: 0.1.0a3
Summary: Add your description here
Author: Bryon Tjanaka
Author-email: Bryon Tjanaka <bryon.tjanaka@gmail.com>
Requires-Python: >=3.12
